fbmsg/__init__.py
fbmsg/errors.py
fbmsg/facebook_client.py
fbmsg/models/__init__.py
fbmsg/models/incoming.py
fbmsg/models/messages.py
fbmsg/models/settings.py
fbmmsg-0.1.dist-info/LICENSE
fbmmsg-0.1.dist-info/METADATA
fbmmsg-0.1.dist-info/WHEEL
fbmmsg-0.1.dist-info/top_level.txt
fbmmsg-0.1.dist-info/RECORD
